{"id":"2qGHFR7CcKOE0Meu7UU6D","title":"Dendron Documentation","vault":{"fsPath":"vault"},"type":"note","desc":"","links":[{"type":"wiki","from":{"fname":"Dendron","id":"2qGHFR7CcKOE0Meu7UU6D","vaultName":"vault"},"value":"https://github.com/dendronhq/dendron/issues/1605","alias":"https://github.com/dendronhq/dendron/issues/1605","position":{"start":{"line":30,"column":1,"offset":1360},"end":{"line":30,"column":53,"offset":1412},"indent":[]},"xvault":false,"sameFile":false,"to":{"fname":"https://github.com/dendronhq/dendron/issues/1605"}},{"type":"wiki","from":{"fname":"Dendron","id":"2qGHFR7CcKOE0Meu7UU6D","vaultName":"vault"},"value":"https://github.com/dendronhq/dendron/issues/547","alias":"https://github.com/dendronhq/dendron/issues/547","position":{"start":{"line":32,"column":1,"offset":1414},"end":{"line":32,"column":52,"offset":1465},"indent":[]},"xvault":false,"sameFile":false,"to":{"fname":"https://github.com/dendronhq/dendron/issues/547"}}],"anchors":{"technical-specifications":{"type":"header","text":"Technical Specifications","value":"technical-specifications","line":8,"column":0},"current-limitations":{"type":"header","text":"Current Limitations","value":"current-limitations","line":24,"column":0},"no-support-for-rendering-academic-citations":{"type":"header","text":"No Support for rendering Academic Citations","value":"no-support-for-rendering-academic-citations","line":26,"column":0},"no-renderexport-to-pdf":{"type":"header","text":"No render/export to PDF","value":"no-renderexport-to-pdf","line":40,"column":0},"narrow-stylesheet":{"type":"header","text":"Narrow stylesheet","value":"narrow-stylesheet","line":48,"column":0},"no-code-output":{"type":"header","text":"No Code output","value":"no-code-output","line":52,"column":0}},"fname":"Dendron","updated":1636514167375,"created":1636096635240,"parent":"PhD","children":[],"data":{},"contentHash":"19e3eab91556ba93697eef01f1066d73","custom":{}}
