{"id":"GLHB2UVCnE6nVxFI7vDeE","title":"Empirical Study","vault":{"fsPath":"vault"},"type":"note","desc":"","links":[],"anchors":{"inflation-forecasting":{"type":"header","text":"Inflation Forecasting","value":"inflation-forecasting","line":14,"column":0},"gdp-forecasting":{"type":"header","text":"GDP forecasting","value":"gdp-forecasting","line":19,"column":0},"unemployment-forecasting":{"type":"header","text":"Unemployment forecasting","value":"unemployment-forecasting","line":22,"column":0}},"fname":"CWF.empirical","updated":1636331440143,"created":1636095716715,"parent":"MsmFdXyWfizd5g8GGcObD","children":["6jScjSKL9hxSIPTbWMgAH"],"data":{},"contentHash":"4ddc68b411fab7bb61f300f96eab7e99","custom":{}}
