{"id":"jU02nYSOp3VgANjM","title":"Dev","vault":{"fsPath":"templates","seed":"dendron.templates","name":"dendron.templates"},"type":"note","desc":"","links":[],"anchors":{"build":{"type":"header","text":"Build","value":"build","line":8,"column":0},"prerequisites":{"type":"header","text":"Prerequisites","value":"prerequisites","line":10,"column":0},"steps":{"type":"header","text":"Steps","value":"steps","line":13,"column":0},"run":{"type":"header","text":"Run","value":"run","line":16,"column":0}},"fname":"templates.module.dev","updated":1627142693960,"created":1627142619514,"parent":"xIwvEqQ71wRQ4wWk","children":["S6kgW0w5C7p2kzldJGQyi"],"data":{},"contentHash":"fe0aa9a9d56bd787145cb0a90870a57c","custom":{}}
